ait/commons/util/__init__.py
ait/commons/util/__main__.py
ait/commons/util/aws_client.py
ait/commons/util/aws_cognito_authenticator.py
ait/commons/util/bucket_policy.py
ait/commons/util/cmd.py
ait/commons/util/common.py
ait/commons/util/file_transfer.py
ait/commons/util/local_state.py
ait/commons/util/progress_bar.py
ait/commons/util/upload_service.py
ait/commons/util/user_profile.py
ait/commons/util/command/__init__.py
ait/commons/util/command/area.py
ait/commons/util/command/config.py
ait/commons/util/command/create.py
ait/commons/util/command/delete.py
ait/commons/util/command/download.py
ait/commons/util/command/list.py
ait/commons/util/command/select.py
ait/commons/util/command/sync.py
ait/commons/util/command/upload.py
ait/commons/util/settings/__init__.py
ait/commons/util/settings/hca_util.py
ait/commons/util/settings/morphic_util.py
morphic_util-0.0.9.dist-info/LICENSE
morphic_util-0.0.9.dist-info/METADATA
morphic_util-0.0.9.dist-info/WHEEL
morphic_util-0.0.9.dist-info/entry_points.txt
morphic_util-0.0.9.dist-info/top_level.txt
morphic_util-0.0.9.dist-info/RECORD
