Metadata-Version: 2.1
Name: morphic-util
Version: 0.0.9
Summary: CLI tool for uploading data to Morphic AWS S3 bucket
Home-page: https://github.com/ebi-ait/morphic-util
Author: hca-ingest-dev
Author-email: hca-ingest-dev@ebi.ac.uk
License: Apache License
Platform: MacOS X
Platform: Posix
Classifier: License :: OSI Approved :: Apache Software License
Classifier: Operating System :: MacOS :: MacOS X
Classifier: Operating System :: POSIX
Classifier: Programming Language :: Python :: 3.6
Classifier: Programming Language :: Python :: 3.7
Requires-Python: >=3.6
License-File: LICENSE
Requires-Dist: boto3 (>=1.26.153)
Requires-Dist: botocore (>=1.29.153)
Requires-Dist: filetype (==1.0.7)
Requires-Dist: requests (<3,>=2.20.0)
Requires-Dist: urllib3 (<1.27,>=1.25.4)
Requires-Dist: tqdm
